graph_project/__init__.py
graph_project/main.py
graph_project-0.0.5.dist-info/METADATA
graph_project-0.0.5.dist-info/WHEEL
graph_project-0.0.5.dist-info/licenses/LICENSE
graph_project-0.0.5.dist-info/RECORD
