Metadata-Version: 2.4
Name: graph_project
Version: 0.0.5
Author: Fyodor K
Author-email: Vladislav R <radionovvladislav32@gmail.com>
License-File: LICENSE
Classifier: License :: OSI Approved :: MIT License
Classifier: Operating System :: OS Independent
Classifier: Programming Language :: Python :: 3
Requires-Python: >=3.10.0
Requires-Dist: matplotlib
Requires-Dist: networkx
Requires-Dist: openpyxl
